leprikon/__init__.py
leprikon/__main__.py
leprikon/admin/__init__.py
leprikon/admin/account.py
leprikon/admin/activities.py
leprikon/admin/agegroup.py
leprikon/admin/agreements.py
leprikon/admin/bulkupdate.py
leprikon/admin/calendar.py
leprikon/admin/citizenship.py
leprikon/admin/courses.py
leprikon/admin/department.py
leprikon/admin/donation.py
leprikon/admin/events.py
leprikon/admin/export.py
leprikon/admin/filters.py
leprikon/admin/journals.py
leprikon/admin/leprikonsite.py
leprikon/admin/messages.py
leprikon/admin/orderables.py
leprikon/admin/organizations.py
leprikon/admin/pdf.py
leprikon/admin/place.py
leprikon/admin/printsetup.py
leprikon/admin/question.py
leprikon/admin/refundrequest.py
leprikon/admin/registrationlink.py
leprikon/admin/roles.py
leprikon/admin/school.py
leprikon/admin/schoolyear.py
leprikon/admin/sendmail.py
leprikon/admin/settings.py
leprikon/admin/statgroup.py
leprikon/admin/targetgroup.py
leprikon/admin/timesheets.py
leprikon/admin/transaction.py
leprikon/admin/user.py
leprikon/admin/utils.py
leprikon/api/__init__.py
leprikon/api/openapi.py
leprikon/api/serializers.py
leprikon/api/urls.py
leprikon/api/views.py
leprikon/apps.py
leprikon/bankreaders.py
leprikon/cms_apps.py
leprikon/cms_menus.py
leprikon/cms_plugins/__init__.py
leprikon/cms_plugins/base.py
leprikon/cms_plugins/courses.py
leprikon/cms_plugins/events.py
leprikon/cms_plugins/leaders.py
leprikon/cms_plugins/orderables.py
leprikon/cms_plugins/schoolyears.py
leprikon/cms_toolbars.py
leprikon/conf/__init__.py
leprikon/conf/default_settings.py
leprikon/cronjobs.py
leprikon/forms/__init__.py
leprikon/forms/activities.py
leprikon/forms/billing_info.py
leprikon/forms/confirm.py
leprikon/forms/courses.py
leprikon/forms/fields.py
leprikon/forms/form.py
leprikon/forms/journals.py
leprikon/forms/leaders.py
leprikon/forms/messages.py
leprikon/forms/parent.py
leprikon/forms/participant.py
leprikon/forms/refundrequest.py
leprikon/forms/registrationlink.py
leprikon/forms/reports/__init__.py
leprikon-4.5.1.dist-info/METADATA
leprikon-4.5.1.dist-info/WHEEL
leprikon-4.5.1.dist-info/entry_points.txt
leprikon-4.5.1.dist-info/licenses/LICENSE
leprikon-4.5.1.dist-info/RECORD
